{
  "tuf-spec": {
    "1.0.24": "tuf-spec/tuf-spec/1.0.24/specification-1.0.24.zip",
    "1.0.25": "tuf-spec/tuf-spec/1.0.25/specification-1.0.25.zip",
    "1.0.26": "tuf-spec/tuf-spec/1.0.26/specification-1.0.26.zip",
    "1.0.27": "tuf-spec/tuf-spec/1.0.27/specification-1.0.27.zip",
    "1.0.28": "tuf-spec/tuf-spec/1.0.28/specification-1.0.28.zip",
    "1.0.29": "tuf-spec/tuf-spec/1.0.29/specification-1.0.29.zip",
    "1.0.30": "tuf-spec/tuf-spec/1.0.30/specification-1.0.30.zip"
  },
  "tarball": {
    "1.0.24": "tuf-spec/tarball/1.0.24/specification-1.0.24.tar.gz",
    "1.0.25": "tuf-spec/tarball/1.0.25/specification-1.0.25.tar.gz",
    "1.0.26": "tuf-spec/tarball/1.0.26/specification-1.0.26.tar.gz",
    "1.0.27": "tuf-spec/tarball/1.0.27/specification-1.0.27.tar.gz",
    "1.0.28": "tuf-spec/tarball/1.0.28/specification-1.0.28.tar.gz",
    "1.0.29": "tuf-spec/tarball/1.0.29/specification-1.0.29.tar.gz",
    "1.0.30": "tuf-spec/tarball/1.0.30/specification-1.0.30.tar.gz"
  }
}

